retry/__init__.py
retry/api.py
retry/compat.py
fork_from_retry-0.12.0.dist-info/LICENSE
fork_from_retry-0.12.0.dist-info/METADATA
fork_from_retry-0.12.0.dist-info/WHEEL
fork_from_retry-0.12.0.dist-info/top_level.txt
fork_from_retry-0.12.0.dist-info/RECORD
